pymdrive/__init__.py
pymdrive/axis.py
pymdrive/comm.py
pymdrive-1.0.0.dist-info/METADATA
pymdrive-1.0.0.dist-info/WHEEL
pymdrive-1.0.0.dist-info/RECORD
