Metadata-Version: 2.4
Name: pymdrive
Version: 1.0.0
Summary: Add your description here
Author-email: jgobbo <59982706+jgobbo@users.noreply.github.com>
Requires-Python: >=3.9
Requires-Dist: pyserial>=3.5
